proquo/__init__.py
proquo/cli/Helper.py
proquo/cli/OptionValueCheckAction.py
proquo/cli/ProQuoCLI.py
proquo/cli/ProQuoLmCLI.py
proquo/cli/__init__.py
proquo/core/Helper.py
proquo/core/ProQuo.py
proquo/core/ProQuoLm.py
proquo/core/Quote.py
proquo/core/QuoteRef.py
proquo/core/Reference.py
proquo/core/__init__.py
proquo/match/MatchRef.py
proquo/match/__init__.py
proquo/model/__init__.py
proquo/model/linking/LinkingModelTrainer.py
proquo/model/linking/LinkingVectorizer.py
proquo/model/linking/__init__.py
proquo/model/reference/ReferenceModelTrainer.py
proquo/model/reference/ReferenceVectorizer.py
proquo/model/reference/__init__.py
proquo/model/relation/RelationModelBertTrainer.py
proquo/model/relation/RelationModelLstmTrainer.py
proquo/model/relation/RelationVectorizerBert.py
proquo/model/relation/RelationVectorizerLstm.py
proquo/model/relation/__init__.py
proquo/testing/__init__.py
proquo/testing/linking/TestLinking.py
proquo/testing/linking/__init__.py
proquo/testing/reference/TestReference.py
proquo/testing/reference/__init__.py
proquo/testing/relation/TestRelationBert.py
proquo/testing/relation/TestRelationLstm.py
proquo/testing/relation/__init__.py
proquo/training/__init__.py
proquo/training/linking/TrainLinking.py
proquo/training/linking/__init__.py
proquo/training/reference/TrainReference.py
proquo/training/reference/__init__.py
proquo/training/relation/TrainRelationBert.py
proquo/training/relation/TrainRelationLstm.py
proquo/training/relation/__init__.py
ProQuo-1.1.1.dist-info/LICENSE
ProQuo-1.1.1.dist-info/METADATA
ProQuo-1.1.1.dist-info/WHEEL
ProQuo-1.1.1.dist-info/entry_points.txt
ProQuo-1.1.1.dist-info/top_level.txt
ProQuo-1.1.1.dist-info/RECORD
