Metadata-Version: 2.1
Name: ProQuo
Version: 1.1.1
Summary: ProQuo is a tool for the detection of short quotations (<= 4 words) between two texts, a source text and a target text. The target text is the text quoting the source text. Quotations in the target text need to be clearly marked with quotations marks.
Author-email: Frederik Arnold <frederik.arnold@hu-berlin.de>
License: Apache License
Project-URL: Homepage, https://hu.berlin/proquo
Keywords: quotation detection,quotation identification,literal citation extraction,natural language processing,nlp,text reuse
Classifier: Programming Language :: Python :: 3
Classifier: License :: OSI Approved :: Apache Software License
Classifier: Operating System :: OS Independent
Requires-Python: >=3.9
License-File: LICENSE
Requires-Dist: quid ~=2.6.1
Requires-Dist: kpcommons ~=0.0.2
Requires-Dist: transformers ~=4.39.3
Requires-Dist: torch ~=2.2.2
Requires-Dist: scikit-learn ~=1.2.1
Requires-Dist: keras-preprocessing ~=1.1.2
